basinmaker/__init__.py
basinmaker/basinmaker.py
basinmaker/addattributes/__init__.py
basinmaker/addattributes/addattributestocatchments.py
basinmaker/addattributes/addgaugeattributesqgis.py
basinmaker/addattributes/addlakeattributesqgis.py
basinmaker/addattributes/calbkfwidthdepthqgis.py
basinmaker/addattributes/calculatebasicattributesqgis.py
basinmaker/addattributes/calfloodmanningnqgis.py
basinmaker/addattributes/createattributestemplatearcgis.py
basinmaker/addattributes/createattributestemplateqgis.py
basinmaker/addattributes/exportoutputsqgis.py
basinmaker/addattributes/joinpandastoattributesqgis.py
basinmaker/addlakeandobs/__init__.py
basinmaker/addlakeandobs/addlakeandobsintowatershed.py
basinmaker/addlakeandobs/addlakesarcgis.py
basinmaker/addlakeandobs/addlakesqgis.py
basinmaker/addlakeandobs/addobsarcgis.py
basinmaker/addlakeandobs/addobsqgis.py
basinmaker/addlakeandobs/definecatrivarcgis.py
basinmaker/addlakeandobs/definecatrivqgis.py
basinmaker/addlakeandobs/definelaketypeqgis.py
basinmaker/addlakeandobs/filterlakesqgis.py
basinmaker/addlakeandobs/modifyfdr.py
basinmaker/addlakeandobs/modifystr.py
basinmaker/addlakeandobs/pourpointsqgis.py
basinmaker/arcgisguiwarpper/__init__.py
basinmaker/arcgisguiwarpper/generatehru_arcgis_wrapper.py
basinmaker/arcgisguiwarpper/generateraveninput_arcgis_wrapper.py
basinmaker/arcgisguiwarpper/selectprod_arcgis_wrapper.py
basinmaker/arcgisguiwarpper/simplyda_arcgis_wrapper.py
basinmaker/arcgisguiwarpper/simplylakes_arcgis_wrapper.py
basinmaker/delineationnolake/__init__.py
basinmaker/delineationnolake/watdelineationwithoutlake.py
basinmaker/delineationnolake/watusingdemarcgis.py
basinmaker/delineationnolake/watusingdemqgis.py
basinmaker/delineationnolake/watusingfacqgis.py
basinmaker/delineationnolake/watusingfdrarcgis.py
basinmaker/delineationnolake/watusingfdrqgis.py
basinmaker/delineationnolake/watusingsubregionddata.py
basinmaker/extent/__init__.py
basinmaker/extent/projectextent.py
basinmaker-3.1.0.dist-info/LICENSE
basinmaker-3.1.0.dist-info/METADATA
basinmaker-3.1.0.dist-info/WHEEL
basinmaker-3.1.0.dist-info/top_level.txt
basinmaker-3.1.0.dist-info/RECORD
