Metadata-Version: 2.1
Name: basinmaker
Version: 3.1.0
Summary: An automated GIS toolbox for watershed delineation with lakes
Home-page: https://github.com/dustming/basinmaker
Author: basinmaker development team
Author-email: m43han@uwaterloo.ca
Classifier: Programming Language :: Python :: 3
Classifier: License :: OSI Approved :: MIT License
Classifier: Operating System :: OS Independent
Requires-Python: >=3.5
License-File: LICENSE
